shadowed/__init__.py
shadowed-0.0.1.dist-info/LICENSE.txt
shadowed-0.0.1.dist-info/METADATA
shadowed-0.0.1.dist-info/WHEEL
shadowed-0.0.1.dist-info/top_level.txt
shadowed-0.0.1.dist-info/RECORD
