Metadata-Version: 2.1
Name: shadowed
Version: 0.0.1
Summary: Manage file changes with shadowed copies.
Home-page: https://github.com/christophevg/shadowed
Author: Christophe VG
License: MIT
Keywords: shadow copies changes
Platform: UNKNOWN
Classifier: Development Status :: 4 - Beta
Classifier: Intended Audience :: Developers
Classifier: Programming Language :: Python :: 3
Requires-Dist: fs
Requires-Dist: diff-match-patch
